gempaterkini/__init__.py
latestearthquake_ind-0.2.dist-info/LICENSE
latestearthquake_ind-0.2.dist-info/METADATA
latestearthquake_ind-0.2.dist-info/WHEEL
latestearthquake_ind-0.2.dist-info/top_level.txt
latestearthquake_ind-0.2.dist-info/RECORD
