Metadata-Version: 2.1
Name: latestearthquake-ind
Version: 0.2
Summary: This package will get the latest info of earquake from BMKG (Meteorological, Climatological, and Geophysical Agency)
Home-page: https://github.com/dodevdi/latest-indonesia-earthquake
Author: dodi ackbar
Author-email: dodiakbar.tgr@gmail.com
Project-URL: Website, https://github.com/dodevdi/
Classifier: Programming Language :: Python :: 3
Classifier: License :: OSI Approved :: GNU General Public License v3 (GPLv3)
Classifier: Operating System :: OS Independent
Classifier: Development Status :: 5 - Production/Stable
Requires-Python: >=3.6
License-File: LICENSE
